langeval/__about__.py
langeval/__init__.py
langeval/__main__.py
langeval/cli/__init__.py
langeval/cli/application.py
langeval/cli/constant.py
langeval/cli/terminal.py
langeval/cli/rerun/__init__.py
langeval/cli/run/__init__.py
langeval/cli/run/display.py
langeval/cli/run/run.py
langeval/cli/show/__init__.py
langeval/config/__init__.py
langeval/evaluators/__init__.py
langeval/evaluators/evaluator.py
langeval/evaluators/exception.py
langeval/evaluators/run.py
langeval/evaluators/nlp/__init__.py
langeval/evaluators/rag/__init__.py
langeval/evaluators/rag/utils.py
langeval/evaluators/sql/__init__.py
langeval/evaluators/sql/sqleval.py
langeval/models/__init__.py
langeval/models/embeddings.py
langeval/models/exception.py
langeval/models/llms.py
langeval/models/openai.py
langeval/models/qianfan.py
langeval/models/types.py
langeval/providers/__init__.py
langeval/providers/exception.py
langeval/providers/output_parser.py
langeval/providers/provider.py
langeval/providers/run.py
langeval/tasks/__init__.py
langeval/tasks/ratelimiter.py
langeval/tasks/runner.py
langeval/tasks/task.py
langeval_cli-0.4.0.dist-info/METADATA
langeval_cli-0.4.0.dist-info/WHEEL
langeval_cli-0.4.0.dist-info/entry_points.txt
langeval_cli-0.4.0.dist-info/licenses/LICENSE
langeval_cli-0.4.0.dist-info/RECORD
