Metadata-Version: 2.1
Name: langeval-cli
Version: 0.4.0
Summary: Evaluation for AI apps and agent.
Project-URL: Documentation, https://github.com/ninehills/langeval#readme
Project-URL: Issues, https://github.com/ninehills/langeval/issues
Project-URL: Source, https://github.com/ninehills/langeval
Author-email: Tao Yang <swulling@gmail.com>
License-Expression: MIT
License-File: LICENSE
Classifier: Development Status :: 4 - Beta
Classifier: Programming Language :: Python
Classifier: Programming Language :: Python :: 3.10
Classifier: Programming Language :: Python :: 3.11
Classifier: Programming Language :: Python :: Implementation :: CPython
Classifier: Programming Language :: Python :: Implementation :: PyPy
Requires-Python: >=3.7
Requires-Dist: click~=8.0
Requires-Dist: func-timeout
Requires-Dist: jieba
Requires-Dist: jinja2
Requires-Dist: nltk
Requires-Dist: numpy~=1.0
Requires-Dist: openai>1.0
Requires-Dist: pandas
Requires-Dist: pydantic
Requires-Dist: python-dotenv
Requires-Dist: pyyaml
Requires-Dist: rich~=13.0
Requires-Dist: rouge-chinese
Requires-Dist: scikit-learn
Requires-Dist: sqlalchemy
